bazaar_of_wonders/.env
bazaar_of_wonders/__init__.py
bazaar_of_wonders/asgi.py
bazaar_of_wonders/settings.py
bazaar_of_wonders/urls.py
bazaar_of_wonders/wsgi.py
bazaar_of_wonders_db/db.sqlite3
bazaar_of_wonders_server_scripts/init.py
bazaar_of_wonders_server_scripts/run.py
main/__init__.py
main/admin.py
main/apps.py
main/forms.py
main/models.py
main/serializers.py
main/urls.py
main/views.py
main/migrations/0001_initial.py
main/migrations/0002_collection_collection_content.py
main/migrations/0003_auto_20200619_0110.py
main/migrations/0004_auto_20200619_1245.py
main/migrations/0005_auto_20200621_1449.py
main/migrations/0006_auto_20200625_0009.py
main/migrations/0007_auto_20200625_0408.py
main/migrations/0008_auto_20200625_0829.py
main/migrations/0009_auto_20200626_0250.py
main/migrations/0010_auto_20200626_0509.py
main/migrations/0011_alter_bazaar_user_auth_user_id.py
main/migrations/0012_auto_20200715_1817.py
main/migrations/0013_auto_20200715_1946.py
main/migrations/0014_seller_seller_user.py
main/migrations/0015_auto_20200716_0037.py
main/migrations/0016_auto_20200716_2037.py
main/migrations/0017_alter_bazaar_user_location.py
main/migrations/0018_user_preferences.py
main/migrations/0019_auto_20200716_2117.py
main/migrations/0020_auto_20200717_1639.py
main/migrations/0021_user_preferences_pref_test.py
main/migrations/0022_auto_20200717_1727.py
main/migrations/0023_auto_20200717_1731.py
main/migrations/0024_auto_20200718_2213.py
main/migrations/0025_alter_notification_unique_together.py
main/migrations/0026_remove_notification_seller_key.py
main/migrations/0027_auto_20200724_2226.py
main/migrations/0028_auto_20200729_0700.py
main/migrations/0029_auto_20200729_0800.py
main/migrations/0030_auto_20200730_0744.py
main/migrations/0031_auto_20200801_2108.py
main/migrations/__init__.py
main/scripts/Lower price on notifications for testing.py
main/scripts/__init__.py
main/scripts/mass_data_update.py
main/scripts/notifications.py
main/scripts/notify.py
django_bazaar_of_wonders-0.1.40.dist-info/METADATA
django_bazaar_of_wonders-0.1.40.dist-info/WHEEL
django_bazaar_of_wonders-0.1.40.dist-info/entry_points.txt
django_bazaar_of_wonders-0.1.40.dist-info/top_level.txt
django_bazaar_of_wonders-0.1.40.dist-info/RECORD
