Metadata-Version: 2.1
Name: django-bazaar-of-wonders
Version: 0.1.40
Summary: Bazaar of Wonders is a Django-based web application that aggregates card details and pricing statistics for trading card games, namely, Magic: The Gathering.
Home-page: https://github.com/Bazaar-Trader/Bazaar_Of_Wonders
Author: https://github.com/Bazaar-Trader
License: UNKNOWN
Platform: UNKNOWN
Classifier: Programming Language :: Python :: 3
Classifier: Operating System :: OS Independent
Requires-Python: >=3.8
Requires-Dist: django
Requires-Dist: django-tinymce4-lite
Requires-Dist: django-materializecss-form
Requires-Dist: PyYAML
Requires-Dist: bs4
Requires-Dist: django-environ
Requires-Dist: apscheduler
